cria_index/plugins/tools/arxiv/__init__.py
cria_index/plugins/tools/arxiv/base.py
cria_index_tool_plugin_arxiv-0.1.0.dist-info/METADATA
cria_index_tool_plugin_arxiv-0.1.0.dist-info/WHEEL
cria_index_tool_plugin_arxiv-0.1.0.dist-info/RECORD
